demo/__init__.py
demo/main.py
BMeyn-0.19.2.dist-info/LICENSE
BMeyn-0.19.2.dist-info/METADATA
BMeyn-0.19.2.dist-info/WHEEL
BMeyn-0.19.2.dist-info/top_level.txt
BMeyn-0.19.2.dist-info/RECORD
