Metadata-Version: 2.1
Name: BMeyn
Version: 0.19.2
Summary: My project description
Home-page: UNKNOWN
License: UNKNOWN
Platform: UNKNOWN
Requires-Dist: json
